<?xml version="1.0" encoding="utf-8"?>
<Maps>
    <Map Type="System" Name="WITT_RW17_RECIP" Priority="3" Center="+05.5169+095.4200">
        <Runway Name="17">
            <Threshold Name="17" Position="+05.5391+095.4171" ExtendedCentrelineTrack="349" ExtendedCentrelineLength="12" ExtendedCentrelineWidth="1" ExtendedCentrelineTickInterval="1" />
            <Threshold Name="35" Position="+05.5125+095.4226" />
        </Runway>
        <!--SID: ANSA2F, Runway: 35-->
        <Line Pattern="Dotted">+05.5391+095.4171/TT419/TT407/TT408/ANSAX</Line>
        <!--SID: ANSA3B, Runway: 35-->
        <Line Pattern="Dotted">+05.5391+095.4171/ANSAX</Line>
        <!--SID: AVDI1B, Runway: 35-->
        <Line Pattern="Dotted">+05.5391+095.4171/AVDIN</Line>
        <!--SID: AVDI1D, Runway: 35-->
        <Line Pattern="Dotted">+05.5391+095.4171/TEUKU/TT410/AVDIN</Line>
        <!--SID: BULV1B, Runway: 35-->
        <Line Pattern="Dotted">+05.5391+095.4171/EMREB/BULVA</Line>
        <!--SID: BULV1D, Runway: 35-->
        <Line Pattern="Dotted">+05.5391+095.4171/TT414/OTKUL/BULVA</Line>
        <!--SID: DUAM2F, Runway: 35-->
        <Line Pattern="Dotted">+05.5391+095.4171/TEUKU/TT410/DUAMO</Line>
        <!--SID: DUAM3B, Runway: 35-->
        <Line Pattern="Dotted">+05.5391+095.4171/DUAMO</Line>
        <!--SID: ELDE1B, Runway: 35-->
        <Line Pattern="Dotted">+05.5391+095.4171/ELDEL</Line>
        <!--SID: ELDE1D, Runway: 35-->
        <Line Pattern="Dotted">+05.5391+095.4171/TEUKU/BELRI/TT411/UDODO/ELDEL</Line>
        <!--SID: EMRE1B, Runway: 35-->
        <Line Pattern="Dotted">+05.5391+095.4171/EMREB</Line>
        <!--SID: IVRA1B, Runway: 35-->
        <Line Pattern="Dotted">+05.5391+095.4171/IVRAR</Line>
        <!--SID: IVRA1D, Runway: 35-->
        <Line Pattern="Dotted">+05.5391+095.4171/TEUKU/BELRI/TT411/IVRAR</Line>
        <!--SID: OPUN1F, Runway: 35-->
        <Line Pattern="Dotted">+05.5391+095.4171/OPUNG</Line>
        <!--SID: OPUN1H, Runway: 35-->
        <Line Pattern="Dotted">+05.5391+095.4171/TEUKU/TT410/AKBUR/OPUNG</Line>
        <!--SID: OTKU1B, Runway: 35-->
        <Line Pattern="Dotted">+05.5391+095.4171/TT414/OTKUL</Line>
        <!--SID: TASE1C, Runway: 35-->
        <Line Pattern="Dotted">+05.5391+095.4171/DUAMO/TASEK</Line>
        <!--SID: TASE1D, Runway: 35-->
        <Line Pattern="Dotted">+05.5391+095.4171/TEUKU/TT410/DUAMO/TASEK</Line>
        <!--STAR: AKPU1A, Runway: 17-->
        <Line Pattern="Dashed">AKPUM/URDAM/TENOM/TT424/IRMUS/VAVDO</Line>
        <!--STAR: ANSA2C, Runway: 17-->
        <Line Pattern="Dashed">ANSAX/VAVDO</Line>
        <!--STAR: ANSA3D, Runway: 17-->
        <Line Pattern="Dashed">ANSAX/UPSOL/VAVDO</Line>
        <!--STAR: BUDG1A, Runway: 17-->
        <Line Pattern="Dashed">BUDGA/D137T/VAVDO</Line>
        <!--STAR: BUDG1B, Runway: 17-->
        <Line Pattern="Dashed">BUDGA/UDODO/TT409/TT425/TT427/UPSOL/VAVDO</Line>
        <!--STAR: BULV1E, Runway: 17-->
        <Line Pattern="Dashed">BULVA/UDOLI/D237T/VAVDO</Line>
        <!--STAR: DUAM3C, Runway: 17-->
        <Line Pattern="Dashed">DUAMO/D098T/VAVDO</Line>
        <!--STAR: DUAM3D, Runway: 17-->
        <Line Pattern="Dashed">DUAMO/LAWAH/TT413/TT425/TT427/UPSOL/VAVDO</Line>
        <!--STAR: ELDE1E, Runway: 17-->
        <Line Pattern="Dashed">ELDEL/D143T/VAVDO</Line>
        <!--STAR: ELDE1F, Runway: 17-->
        <Line Pattern="Dashed">ELDEL/UDODO/TT409/TT425/TT427/UPSOL/VAVDO</Line>
        <!--STAR: IVRA1E, Runway: 17-->
        <Line Pattern="Dashed">IVRAR/D151T/VAVDO</Line>
        <!--STAR: IVRA1F, Runway: 17-->
        <Line Pattern="Dashed">IVRAR/UDODO/TT409/TT425/TT427/UPSOL/VAVDO</Line>
        <!--STAR: OPUN1J, Runway: 17-->
        <Line Pattern="Dashed">OPUNG/D123T/VAVDO</Line>
        <!--STAR: OPUN1K, Runway: 17-->
        <Line Pattern="Dashed">OPUNG/AKBUR/TT409/TT425/TT427/UPSOL/VAVDO</Line>
        <!--STAR: TASE1E, Runway: 17-->
        <Line Pattern="Dashed">TASEK/DUAMO/D098T/VAVDO</Line>
        <!--STAR: TASE1F, Runway: 17-->
        <Line Pattern="Dashed">TASEK/DUAMO/LAWAH/TT413/TT425/TT427/UPSOL/VAVDO</Line>
        <!--STAR: UDOL1A, Runway: 17-->
        <Line Pattern="Dashed">UDOLI/D237T/VAVDO</Line>
        <!--STAR: URDA1A, Runway: 17-->
        <Line Pattern="Dashed">URDAM/TENOM/TT424/IRMUS/VAVDO</Line>
        <Symbol Type="SolidTriangle">
            <Point>D143T</Point>
            <Point>LAWAH</Point>
            <Point>AKPUM</Point>
            <Point>TENOM</Point>
            <Point>TEUKU</Point>
            <Point>TASEK</Point>
            <Point>IVRAR</Point>
            <Point>AKBUR</Point>
            <Point>VAVDO</Point>
            <Point>D137T</Point>
            <Point>BULVA</Point>
            <Point>TT413</Point>
            <Point>DUAMO</Point>
            <Point>D123T</Point>
            <Point>TT419</Point>
            <Point>UDODO</Point>
            <Point>BELRI</Point>
            <Point>TT427</Point>
            <Point>TT409</Point>
            <Point>BUDGA</Point>
            <Point>ANSAX</Point>
            <Point>TT407</Point>
            <Point>TT410</Point>
            <Point>UDOLI</Point>
            <Point>D098T</Point>
            <Point>URDAM</Point>
            <Point>ELDEL</Point>
            <Point>OPUNG</Point>
            <Point>D151T</Point>
            <Point>EMREB</Point>
            <Point>UPSOL</Point>
            <Point>D237T</Point>
            <Point>AVDIN</Point>
            <Point>TT411</Point>
            <Point>TT425</Point>
            <Point>IRMUS</Point>
            <Point>TT408</Point>
            <Point>TT424</Point>
            <Point>TT414</Point>
            <Point>OTKUL</Point>
        </Symbol>
    </Map>
    <Map Type="System" Name="WITT_RW17_RECIP_NAMES" Priority="3" Center="+05.5169+095.4200">
        <Label>
            <Point>D143T</Point>
            <Point>LAWAH</Point>
            <Point>AKPUM</Point>
            <Point>TENOM</Point>
            <Point>TEUKU</Point>
            <Point>TASEK</Point>
            <Point>IVRAR</Point>
            <Point>AKBUR</Point>
            <Point>VAVDO</Point>
            <Point>D137T</Point>
            <Point>BULVA</Point>
            <Point>TT413</Point>
            <Point>DUAMO</Point>
            <Point>D123T</Point>
            <Point>TT419</Point>
            <Point>UDODO</Point>
            <Point>BELRI</Point>
            <Point>TT427</Point>
            <Point>TT409</Point>
            <Point>BUDGA</Point>
            <Point>ANSAX</Point>
            <Point>TT407</Point>
            <Point>TT410</Point>
            <Point>UDOLI</Point>
            <Point>D098T</Point>
            <Point>URDAM</Point>
            <Point>ELDEL</Point>
            <Point>OPUNG</Point>
            <Point>D151T</Point>
            <Point>EMREB</Point>
            <Point>UPSOL</Point>
            <Point>D237T</Point>
            <Point>AVDIN</Point>
            <Point>TT411</Point>
            <Point>TT425</Point>
            <Point>IRMUS</Point>
            <Point>TT408</Point>
            <Point>TT424</Point>
            <Point>TT414</Point>
            <Point>OTKUL</Point>
        </Label>
    </Map>
</Maps>